importwatch
